README.md
cz_emoticon.py
setup.py
cz_emoticon.egg-info/PKG-INFO
cz_emoticon.egg-info/SOURCES.txt
cz_emoticon.egg-info/dependency_links.txt
cz_emoticon.egg-info/entry_points.txt
cz_emoticon.egg-info/requires.txt
cz_emoticon.egg-info/top_level.txt