Metadata-Version: 2.1
Name: cz-emoticon
Version: 0.1.2
Summary: UNKNOWN
Home-page: https://github.com/jdbaigorria/cz_emoticon
Author: Javier Baigorria
Author-email: jdbaigorria@gmail.com
License: MIT
Platform: UNKNOWN
